{"timeStamp":"1/04/2015 12:06:00 PM","countryCode":"SEK","title":"Swedish Kronor","currencies":[{"currencyTitle":"AUD","currencyName":"Australian Dollar","bbImt":"0.1600025600","bbForeignCheques":"0","bbCashTChqs":"0.1658759911","bsImt":"0.1475122066","bsCashTmcTChqs":"0.1378302758"},{"currencyTitle":"USD","currencyName":"US Dollar","bbImt":"0.1182643151","bbForeignCheques":"0","bbCashTChqs":"0.1182643151","bsImt":"0.1135409634","bsCashTmcTChqs":"0.1135409634"},{"currencyTitle":"GBP","currencyName":"Great British Pound","bbImt":"0.0813972079","bbForeignCheques":"0","bbCashTChqs":"0.0813972079","bsImt":"0.0750716020","bsCashTmcTChqs":"0.0750716020"},{"currencyTitle":"CAD","currencyName":"Canadian Dollar","bbImt":"0.1529860793","bbForeignCheques":"0","bbCashTChqs":"0.1529860793","bsImt":"0.1410927682","bsCashTmcTChqs":"0.1410927682"},{"currencyTitle":"DKK","currencyName":"Danish Kroner","bbImt":"0.8395940885","bbForeignCheques":"0","bbCashTChqs":"0.8395940885","bsImt":"0.7742176630","bsCashTmcTChqs":"0.7742176630"},{"currencyTitle":"EUR","currencyName":"Euro","bbImt":"0.1124006860","bbForeignCheques":"0","bbCashTChqs":"0.1124006860","bsImt":"0.1036700412","bsCashTmcTChqs":"0.1036700412"},{"currencyTitle":"HKD","currencyName":"Hong Kong Dollar","bbImt":"0.9352268239","bbForeignCheques":"0","bbCashTChqs":"0.9352268239","bsImt":"0.8626128909","bsCashTmcTChqs":"0.8626128909"},{"currencyTitle":"INR","currencyName":"Indian Rupee","bbImt":"7.5453815656","bbForeignCheques":"0","bbCashTChqs":"7.5453815656","bsImt":"6.9432569952","bsCashTmcTChqs":"6.9432569952"},{"currencyTitle":"ILS","currencyName":"Israeli New Shekel","bbImt":"0.4809502207","bbForeignCheques":"0","bbCashTChqs":"0.4809502207","bsImt":"0.4421875529","bsCashTmcTChqs":"0.4421875529"},{"currencyTitle":"JPY","currencyName":"Japanese Yen","bbImt":"14.4833930883","bbForeignCheques":"0","bbCashTChqs":"14.4833930883","bsImt":"13.3589822370","bsCashTmcTChqs":"13.3589822370"},{"currencyTitle":"KWD","currencyName":"Kuwaiti Dinar","bbImt":"0.0363384611","bbForeignCheques":"0","bbCashTChqs":"0.0363384611","bsImt":"0.0334188751","bsCashTmcTChqs":"0.0334188751"},{"currencyTitle":"XPF","currencyName":"New C/Tahiti Franc","bbImt":"13.2837317027","bbForeignCheques":"0","bbCashTChqs":"13.2837317027","bsImt":"12.1173186984","bsCashTmcTChqs":"12.1173186984"},{"currencyTitle":"NZD","currencyName":"New Zealand Dollar","bbImt":"0.1619380745","bbForeignCheques":"0","bbCashTChqs":"0.1619380745","bsImt":"0.1493134499","bsCashTmcTChqs":"0.1493134499"},{"currencyTitle":"NOK","currencyName":"Norwegian Kroner","bbImt":"0.9727691684","bbForeignCheques":"0","bbCashTChqs":"0.9727691684","bsImt":"0.8966259486","bsCashTmcTChqs":"0.8966259486"},{"currencyTitle":"OMR","currencyName":"Oman Rial","bbImt":"0.0466957187","bbForeignCheques":"0","bbCashTChqs":"0.0466957187","bsImt":"0.0426275922","bsCashTmcTChqs":"0.0426275922"},{"currencyTitle":"PGK","currencyName":"P.N.G. Kina","bbImt":"0.3399376691","bbForeignCheques":"0","bbCashTChqs":"0.3399376691","bsImt":"0.2789841354","bsCashTmcTChqs":"0.2789841354"},{"currencyTitle":"PLN","currencyName":"Polish Zloty","bbImt":"0.4581644952","bbForeignCheques":"0","bbCashTChqs":"0.4581644952","bsImt":"0.4219230342","bsCashTmcTChqs":"0.4219230342"},{"currencyTitle":"SAR","currencyName":"Saudi Riyal","bbImt":"0.4526987680","bbForeignCheques":"0","bbCashTChqs":"0.4526987680","bsImt":"0.4171962785","bsCashTmcTChqs":"0.4171962785"},{"currencyTitle":"SGD","currencyName":"Singapore Dollar","bbImt":"0.1657088834","bbForeignCheques":"0","bbCashTChqs":"0.1657088834","bsImt":"0.1527850349","bsCashTmcTChqs":"0.1527850349"},{"currencyTitle":"SBD","currencyName":"Solomon Island Dollar","bbImt":"1.6821068307","bbForeignCheques":"0","bbCashTChqs":"1.6821068307","bsImt":"0.4281883282","bsCashTmcTChqs":"0.4281883282"},{"currencyTitle":"ZAR","currencyName":"South African Rand","bbImt":"1.4666146934","bbForeignCheques":"0","bbCashTChqs":"1.4666146934","bsImt":"1.3475370808","bsCashTmcTChqs":"1.3475370808"},{"currencyTitle":"LKR","currencyName":"Sri Lankan Rupee","bbImt":"16.0980203027","bbForeignCheques":"0","bbCashTChqs":"16.0980203027","bsImt":"14.7878021581","bsCashTmcTChqs":"14.7878021581"},{"currencyTitle":"CHF","currencyName":"Swiss Franc","bbImt":"0.1173026370","bbForeignCheques":"0","bbCashTChqs":"0.1173026370","bsImt":"0.1081601436","bsCashTmcTChqs":"0.1081601436"},{"currencyTitle":"THB","currencyName":"Thai Baht","bbImt":"3.9289061169","bbForeignCheques":"0","bbCashTChqs":"3.9289061169","bsImt":"3.6201741399","bsCashTmcTChqs":"3.6201741399"},{"currencyTitle":"TRY","currencyName":"Turkish Lira","bbImt":"0.3137214043","bbForeignCheques":"0","bbCashTChqs":"0.3137214043","bsImt":"0.2888572942","bsCashTmcTChqs":"0.2888572942"},{"currencyTitle":"AED","currencyName":"U.A.E. Dirham","bbImt":"0.4430966518","bbForeignCheques":"0","bbCashTChqs":"0.4430966518","bsImt":"0.4086618584","bsCashTmcTChqs":"0.4086618584"},{"currencyTitle":"VUV","currencyName":"Vanuatu Vatu","bbImt":"12.9218428974","bbForeignCheques":"0","bbCashTChqs":"12.9218428974","bsImt":"11.2438480606","bsCashTmcTChqs":"11.2438480606"},{"currencyTitle":"VND","currencyName":"Vietnamese Dong","bbImt":"2600.1709352373","bbForeignCheques":"0","bbCashTChqs":"2600.1709352373","bsImt":"2308.8556157141","bsCashTmcTChqs":"2308.8556157141"}]}